<?xml version="1.0" encoding="UTF-8"?>
<?xml-stylesheet type="text/xsl" href="/assets/xsl/opinion.xsl"?>
<case source="us372-0773.html" citation="372 U.S. 773" title="WALKER v. RANDOLPH">
  <opinion type="Opinions &amp; Dissents">
    <n id="p773">773</n>
    <h2>U.S. Supreme Court</h2>
    <h1>WALKER v. RANDOLPH, <a href="./us372-0773.xml#p773">372 U.S. 773</a> (1963)</h1>
    <h4>WALKER v. RANDOLPH, WARDEN. ON PETITION FOR WRIT OF CERTIORARI TO THE CIRCUIT COURT OF WILLIAMSON COUNTY, ILLINOIS. No. 2, Misc. Decided April 22, 1963.</h4>
    <p>Certiorari granted; judgment vacated; and case remanded.</p>
    <p>Petitioner pro se.</p>
    <p>William G. Clark, Attorney General of Illinois, for respondent.</p>
    <p>PER CURIAM.</p>
    <p>The motion for leave to proceed in forma pauperis and the petition for writ of certiorari are granted. The judgment is vacated and the case is remanded for further consideration in light of Gideon v. Wainwright, <a href="./us372-0335.xml#p335">372 U.S. 335</a>.</p>
    <n id="p774">774</n>
  </opinion>
</case>
