<?xml version="1.0" encoding="UTF-8"?>
<case source="us275-0498.html" citation="275 U.S. 498" title="Gypsie Oil Co. v. Escoe">
  <opinion type="Opinions &amp; Dissents">
    <n id="p498">498</n>
    <h>U.S. Supreme Court</h>
    <h>Gypsie Oil Co. v. Escoe, <a href="./us275-0498.xml#p498">275 U.S. 498</a> (1927)</h>
    <h>Gypsie Oil Co. v. Escoe</h>
    <h>No. 572</h>
    <h>Decided Nov. 21, 1927</h>
    <h><a href="./us275-0498.xml#p498">275 U.S. 498</a></h>
    <h>ON PETITION FOR CERTIORARI TO THE</h>
    <h>SUPREME COURT OF OKLAHOMA</h>
    <h>PER CURIAM.</h>
    <h>This petition for certiorari to the Supreme Court of the State of Oklahoma is denied.</h>
    <h>The application was not made in accordance with section 8(a), Act of February 13, 1925, ch. 229, 43 Stat. 936, 940, which provides:</h>
    <h>"No writ of error, appeal, or writ of certiorari . . . shall be allowed or entertained unless application therefor be duly made within three months after the entry of such judgment or decree. . . ."</h>
    <h>The judgment of the Supreme Court was entered March 22, 1927. A timely petition for rehearing was denied June 14, 1927. On June 18, 1927, an application for leave to file a second petition for rehearing was endorsed: "Leave granted to file -- Fred C. Branson, Chief Justice."</h>
    <h>On August 2, 1927, as appears from the minutes, the following proceedings were taken by the court:</h>
    <h>"Gypsy Oil Company v. Escoe et al. Application for leave to file a second petition for rehearing denied; application for oral argument denied.-Fred C. Branso, Chief Justice."</h>
    <h>On September 30, 1927, more than three months after denial of the petition for rehearing (June 14), the present petition for certiorari was filed.</h>
    <h>The running of the time within which proceedings may be initiated here to bring up judgment or decree for review is suspended by the seasonable filing of a petition for</h>
    <h>Page 275 U. S. 499</h>
    <h>rehearing. But it begins to run from the date of denial of such petition, and further suspension cannot be obtained by the mere presentation of a motion for leave to file a second request for rehearing. Morse v. United States, <a href="../us270/us270-0151.xml#p151">270 U. S. 151</a>, <a href="../us270/us270-0151.xml#p153">270 U. S. 153</a>-154.</h>
    <p>If, however, a timely motion for leave to file the second petition is granted and the petition is actually entertained by the court, then the time within which application may be made here for certiorari begins to run from the day when the court denies such second petition.</p>
  </opinion>
</case>
