<?xml version="1.0" encoding="UTF-8"?>
<?xml-stylesheet type="text/xsl" href="/assets/xsl/opinion.xsl"?>
<case source="us577-0495.html" citation="577 U.S. 495" title="Hawkins v. Community Bank">
  <script src="/assets/js/xslt-polyfill.min.js" xmlns="http://www.w3.org/1999/xhtml"></script>
  <opinion type="Per Curiam">
    <n id="p495">495</n>
    <p>NOTICE: This opinion is subject to formal revision before publication in the preliminary print of the United States Reports. Readers are requested to notify the Reporter of Decisions, Supreme Court of the United States, Washington, D. C. 20543, of any typographical or other formal errors, in order that corrections may be made before the preliminary print goes to press.</p>
    <p>SUPREME COURT OF THE UNITED STATES</p>
    <p>No. 14–520</p>
    <p>VALERIE J. HAWKINS and JANICE A. PATTERSON, PETITIONERS v. COMMUNITY BANK of RAYMORE</p>
    <p>on writ of certiorari to the united states court of appeals for the eighth circuit</p>
    <p>[March 22, 2016]</p>
    <p>Per Curiam.</p>
    <p>The judgment is affirmed by an equally divided Court.</p>
  </opinion>
</case>
