<?xml version="1.0" encoding="UTF-8"?>
<case source="us364-0441.html" citation="364 U.S. 441" title="New York, N.H. &amp;amp; H. R. Co. v. Henagan">
  <opinion type="Opinions &amp; Dissents">
    <n id="p441">441</n>
    <h>U.S. Supreme Court</h>
    <h>New York, N.H. &amp; H. R. Co. v. Henagan, <a href="./us364-0441.xml#p441">364 U.S. 441</a> (1960)</h>
    <h>New York, New Haven &amp; Hartford Railroad Co. v. Henagan</h>
    <h>No. 38</h>
    <h>Argued November 8, 1960</h>
    <h>Decided November 21, 1960</h>
    <h><a href="./us364-0441.xml#p441">364 U.S. 441</a></h>
    <h>CERTIORARI TO THE UNITED STATES COURT OF APPEALS</h>
    <h>FOR THE FIRST CIRCUIT</h>
    <h>Syllabus</h>
    <p>In this suit against a railroad under the Federal Employers' Liability Act by a waitress in the grill car of one of the railroad's trains to recover damages for injuries allegedly sustained when an emergency application of the brakes brought the train to a sudden stop, held: the proofs were insufficient to submit to the jury the question whether employer negligence played a part in the emergency application of the brakes which allegedly produced the injury.</p>
    <p>272 F.2d 153, reversed.</p>
    <p>PER CURIAM.</p>
    <p>The respondent was a waitress in the grill car of one of petitioner's trains. She brought this action under the Federal Employers' Liability Act, 45 U.S.C. § 51 et seq., for damages for injuries allegedly sustained when an emergency application of the brakes brought the train to a sudden stop. A jury which heard the case in the District Court for the District of Massachusetts returned a verdict for respondent. The trial judge denied the petitioner's motions for judgment notwithstanding the verdict and for a new trial. The Court of Appeals for the First Circuit affirmed, 272 F.2d 153. We granted certiorari, 362 U.S. 967.</p>
    <p>The train was pulling into petitioner's station at Providence, Rhode Island, for a scheduled stop. One Montell,</p>
    <n id="p442">442</n>
    <p>apparently to commit suicide, stepped on the track from the station platform as the train approached alongside the platform. The engineer made the emergency application of the brakes in an unsuccessful effort to stop the train before it reached Montell. We have examined the trial record, and hold that the proofs were insufficient to submit to the jury the question whether employer negligence played a part in the emergency application of the brakes which allegedly produced the respondent's injury. See Herdman v. Pennsylvania R. Co., <a href="../us352/us352-0518.xml#p518">352 U. S. 518</a>.</p>
    <p>The judgment of the Court of Appeals is reversed, and the cause remanded to the District Court with direction to enter judgment for the petitioner notwithstanding the verdict.</p>
    <p>It is so ordered.</p>
    <p>MR. JUSTICE BLACK and MR. JUSTICE DOUGLAS dissent. They believe there was evidence of negligence sufficient for the jury, as summarized by Judge Woodbury, speaking for a unanimous Court of Appeals. 272 F.2d 153. They also dissent from the direction to enter judgment for the petitioner, since they are of the view that, if there is a reversal, there should be a new trial. See Galloway v. United States, <a href="../us319/us319-0372.xml#p372">319 U. S. 372</a>, <a href="../us319/us319-0372.xml#p396">319 U. S. 396</a> (dissenting opinion).</p>
    <p>For the reasons set forth in his opinion in Rogers v. Missouri Pacific R. Co., <a href="../us352/us352-0500.xml#p500">352 U. S. 500</a>, <a href="../us352/us352-0521.xml#p524">352 U. S. 524</a>, MR. JUSTICE FRANKFURTER is of the view that the writ of certiorari was improvidently granted.</p>
  </opinion>
</case>
